NextcordUtils/InviteTracker.py
NextcordUtils/Music.py
NextcordUtils/Pagination.py
NextcordUtils/__init__.py
NextcordUtils-1.0.dist-info/LICENSE.txt
NextcordUtils-1.0.dist-info/METADATA
NextcordUtils-1.0.dist-info/WHEEL
NextcordUtils-1.0.dist-info/top_level.txt
NextcordUtils-1.0.dist-info/RECORD
