Metadata-Version: 2.1
Name: NextcordUtils
Version: 1.0
Summary: NextcordUtils is a very useful library made to be used with discord.py
Home-page: https://www.github.com/amirdadfar9192/NextcordUtils
Author: toxicrecker Moddified by amirdadfar9192
License: UNKNOWN
Platform: UNKNOWN
Classifier: Programming Language :: Python :: 3
Classifier: License :: OSI Approved :: MIT License
Classifier: Operating System :: OS Independent
Requires-Python: >= 3.6
Requires-Dist: nextcord
Provides-Extra: voice
Requires-Dist: nextcord[voice] ; extra == 'voice'
Requires-Dist: youtube-dl ; extra == 'voice'
